{
  "oracle": "svd_lmhead_energy",
  "tensor": "token_embd.weight",
  "tied_embedding": true,
  "qtype": "Q6_K",
  "shape_vocab_hidden": [
    151936,
    2048
  ],
  "rank_for_energy": {
    "e90": 1662,
    "e95": 1829,
    "e99": 1987,
    "e999": 2037
  },
  "dim": 2048,
  "rank99_fraction_of_dim": 0.97,
  "sigma_max": 124.36660766601562,
  "sigma_min": 2.733288288116455,
  "cond_number": 45.500728607177734,
  "verdict": "FULL-RANK (SVD screening NO-GO \u2014 no compressible structure)",
  "note": "Weight-only spectrum. LM head ~4% of decode; oracle is low priority. Recall half (top-k preserved under rank-r) needs real hidden states \u2014 do only if this says LOW-RANK."
}